sqlite_chronicle.py
sqlite_chronicle-0.4.dist-info/METADATA
sqlite_chronicle-0.4.dist-info/WHEEL
sqlite_chronicle-0.4.dist-info/top_level.txt
sqlite_chronicle-0.4.dist-info/RECORD
