Metadata-Version: 2.4
Name: sqlite-chronicle
Version: 0.4
Summary: Use triggers to maintain a chronicle table of updated/deleted timestamps in SQLite
Author: Simon Willison
License-Expression: Apache-2.0
Project-URL: Homepage, https://github.com/simonw/sqlite-chronicle
Project-URL: Changelog, https://github.com/simonw/sqlite-chronicle/releases
Project-URL: Issues, https://github.com/simonw/sqlite-chronicle/issues
Project-URL: CI, https://github.com/simonw/sqlite-chronicle/actions
Classifier: Topic :: Database
Classifier: Programming Language :: SQL
Provides-Extra: test
Requires-Dist: pytest; extra == "test"
Requires-Dist: sqlite-utils>=4.0a0; extra == "test"
Requires-Dist: cogapp; extra == "test"
